setup.py
imsto_client/__init__.py
imsto_client/_util.py
imsto_client/client.py
imsto_client.egg-info/PKG-INFO
imsto_client.egg-info/SOURCES.txt
imsto_client.egg-info/dependency_links.txt
imsto_client.egg-info/top_level.txt
imsto_client/django/__init__.py
imsto_client/django/storage.py
imsto_client/django/widgets.py