Metadata-Version: 1.1
Name: imsto-client
Version: 1.0.4
Summary: imsto-go client in python, include wrapper of django storage
Home-page: https://github.com/liut/imsto_py
Author: Eagle Liut
Author-email: liutao@liut.cc
License: BSD
Keywords: imsto image storage
Platform: UNKNOWN
Classifier: Development Status :: 3 - Alpha
Classifier: Environment :: Web Environment
Classifier: Intended Audience :: Developers
Classifier: License :: OSI Approved :: MIT License
Classifier: Operating System :: MacOS :: MacOS X
Classifier: Operating System :: POSIX :: Linux
Classifier: Programming Language :: Python
Classifier: Programming Language :: Python :: 2.7
Classifier: Topic :: Communications :: File Sharing
Classifier: Topic :: Internet
Classifier: Topic :: Multimedia :: Graphics
Classifier: Topic :: Utilities
